mypygls/__init__.py
mypygls/__main__.py
mypygls/py.typed
mypygls/server.py
mypygls/timer.py
mypygls-0.0.1.dist-info/METADATA
mypygls-0.0.1.dist-info/WHEEL
mypygls-0.0.1.dist-info/entry_points.txt
mypygls-0.0.1.dist-info/licenses/LICENSE
mypygls-0.0.1.dist-info/RECORD
